slice/__init__.py
slice/img_slice.py
slice/img_slice_utils.py
slice/zy_utils.py
slicess/__init__.py
slicess/img_slice.py
slicess-0.0.6.dist-info/METADATA
slicess-0.0.6.dist-info/WHEEL
slicess-0.0.6.dist-info/top_level.txt
slicess-0.0.6.dist-info/RECORD
