Metadata-Version: 2.1
Name: slicess
Version: 0.0.6
Summary: img slice
Home-page: UNKNOWN
Author: jerry
Author-email: jerry@163.com
License: Apache2.0
Platform: UNKNOWN
